{
  "steps": {
    "T0": {
      "consecutive_failures": 0,
      "last_failure": null,
      "last_success": "2026-06-29T07:14:03.061903",
      "last_status": "ok"
    },
    "T1": {
      "consecutive_failures": 0,
      "last_failure": null,
      "last_success": "2026-06-29T08:30:55.622520",
      "last_status": "ok"
    },
    "T3": {
      "consecutive_failures": 0,
      "last_failure": null,
      "last_success": "2026-06-30T06:06:15.042894",
      "last_status": "ok"
    },
    "T4": {
      "consecutive_failures": 0,
      "last_failure": null,
      "last_success": "2026-06-29T11:22:59.396743",
      "last_status": "ok"
    },
    "T5": {
      "consecutive_failures": 1,
      "last_failure": "2026-06-29T11:34:10.827203",
      "last_success": null,
      "last_error": "object of type 'int' has no len()",
      "last_status": "failed"
    },
    "NIGHT": {
      "consecutive_failures": 0,
      "last_failure": null,
      "last_success": "2026-06-29T15:25:12.445794",
      "last_status": "ok"
    },
    "BATTLE": {
      "consecutive_failures": 0,
      "last_failure": null,
      "last_success": "2026-06-29T16:55:19.253032",
      "last_status": "ok"
    }
  },
  "last_alerts": {}
}