{"timestamp": "2026-06-29T11:33:49.132999", "snapshot": {"timestamp": "2026-06-29T11:33:53.079995", "source": "eastmoney_api", "stocks": [{"code": "000404", "full_code": "sz000404", "name": "长虹华意", "price": 8.06, "pct_chg": 8.77, "change": 0.65, "volume": 431147.0, "amount": 344061504.81, "amplitude": 6.07, "turnover": 6.22, "pe": 12.16, "volume_ratio": 3.7, "high": 8.15, "low": 7.7, "open": 7.7, "prev_close": 7.41, "total_mv": 5609727591.0, "float_mv": 5583389671.0, "pb": 1.34, "cloud_score": 8, "cloud_signals": ["MOMENTUM_OK", "TURNOVER_OK", "VOL_BOOM", "CAP_SWEET", "AMPLITUDE_ACTIVE"]}, {"code": "000417", "full_code": "sz000417", "name": "合百集团", "price": 8.6, "pct_chg": 6.04, "change": 0.49, "volume": 1105108.0, "amount": 929297635.55, "amplitude": 7.4, "turnover": 14.19, "pe": 26.08, "volume_ratio": 1.32, "high": 8.66, "low": 8.06, "open": 8.09, "prev_close": 8.11, "total_mv": 6707004120.0, "float_mv": 6699636079.0, "pb": 1.41, "cloud_score": 8, "cloud_signals": ["MOMENTUM_OK", "TURNOVER_HIGH", "VOL_EXPAND", "CAP_SWEET", "AMPLITUDE_ACTIVE"]}, {"code": "000420", "full_code": "sz000420", "name": "吉林化纤", "price": 4.2, "pct_chg": 4.22, "change": 0.17, "volume": 1592950.0, "amount": 678090503.41, "amplitude": 7.94, "turnover": 6.48, "pe": 94.75, "volume_ratio": 2.04, "high": 4.43, "low": 4.11, "open": 4.16, "prev_close": 4.03, "total_mv": 10327247041.0, "float_mv": 10323749701.0, "pb": 2.33, "cloud_score": 8, "cloud_signals": ["MOMENTUM_OK", "TURNOVER_OK", "VOL_BOOM", "CAP_SWEET", "AMPLITUDE_ACTIVE"]}, {"code": "000008", "full_code": "sz000008", "name": "神州高铁", "price": 2.35, "pct_chg": 4.44, "change": 0.1, "volume": 491415.0, "amount": 111727018.72, "amplitude": 9.33, "turnover": 1.81, "pe": -52.49, "volume_ratio": 1.71, "high": 2.38, "low": 2.17, "open": 2.25, "prev_close": 2.25, "total_mv": 6383487555.0, "float_mv": 6383297837.0, "pb": 2.96, "cloud_score": 6, "cloud_signals": ["MOMENTUM_OK", "VOL_EXPAND", "CAP_SWEET", "AMPLITUDE_ACTIVE"]}, {"code": "000017", "full_code": "sz000017", "name": "深中华A", "price": 5.56, "pct_chg": 10.1, "change": 0.51, "volume": 215093.0, "amount": 115464741.14, "amplitude": 13.66, "turnover": 4.88, "pe": 156.64, "volume_ratio": 2.41, "high": 5.56, "low": 4.87, "open": 5.09, "prev_close": 5.05, "total_mv": 3831868227.0, "float_mv": 2450970048.0, "pb": 9.82, "cloud_score": 6, "cloud_signals": ["TURNOVER_OK", "VOL_BOOM", "CAP_SWEET", "AMPLITUDE_ACTIVE"]}, {"code": "000061", "full_code": "sz000061", "name": "农 产 品", "price": 5.51, "pct_chg": 3.77, "change": 0.2, "volume": 314407.0, "amount": 171139838.15, "amplitude": 8.47, "turnover": 1.75, "pe": 20.25, "volume_ratio": 1.4, "high": 5.63, "low": 5.18, "open": 5.31, "prev_close": 5.31, "total_mv": 10937136201.0, "float_mv": 9886659054.0, "pb": 1.28, "cloud_score": 6, "cloud_signals": ["MOMENTUM_OK", "VOL_EXPAND", "CAP_SWEET", "AMPLITUDE_ACTIVE"]}, {"code": "000153", "full_code": "sz000153", "name": "丰原药业", "price": 5.2, "pct_chg": 3.59, "change": 0.18, "volume": 114507.0, "amount": 58555818.2, "amplitude": 5.98, "turnover": 2.5, "pe": 16.32, "volume_ratio": 1.62, "high": 5.25, "low": 4.95, "open": 5.01, "prev_close": 5.02, "total_mv": 2416364714.0, "float_mv": 2386116184.0, "pb": 1.13, "cloud_score": 6, "cloud_signals": ["MOMENTUM_OK", "VOL_EXPAND", "CAP_SWEET", "AMPLITUDE_ACTIVE"]}, {"code": "000070", "full_code": "sz000070", "name": "特发信息", "price": 20.37, "pct_chg": -8.61, "change": -1.92, "volume": 1071879.0, "amount": 2235147384.95, "amplitude": 10.27, "turnover": 12.51, "pe": -463.8, "volume_ratio": 0.94, "high": 22.35, "low": 20.06, "open": 21.89, "prev_close": 22.29, "total_mv": 17689164371.0, "float_mv": 17451529825.0, "pb": 17.68, "cloud_score": 5, "cloud_signals": ["TURNOVER_HIGH", "CAP_SWEET", "AMPLITUDE_ACTIVE"]}, {"code": "000403", "full_code": "sz000403", "name": "派林生物", "price": 9.17, "pct_chg": 3.5, "change": 0.31, "volume": 207120.0, "amount": 187806369.0, "amplitude": 10.38, "turnover": 2.2, "pe": 94.86, "volume_ratio": 0.98, "high": 9.46, "low": 8.54, "open": 8.83, "prev_close": 8.86, "total_mv": 8715144030.0, "float_mv": 8626071170.0, "pb": 1.07, "cloud_score": 5, "cloud_signals": ["MOMENTUM_OK", "CAP_SWEET", "AMPLITUDE_ACTIVE"]}, {"code": "000411", "full_code": "sz000411", "name": "英特集团", "price": 9.23, "pct_chg": 2.56, "change": 0.23, "volume": 72464.0, "amount": 65063393.05, "amplitude": 7.89, "turnover": 1.29, "pe": 16.26, "volume_ratio": 1.31, "high": 9.33, "low": 8.62, "open": 8.95, "prev_close": 9.0, "total_mv": 5213557618.0, "float_mv": 5203282689.0, "pb": 0.96, "cloud_score": 5, "cloud_signals": ["MOMENTUM_WEAK", "VOL_EXPAND", "CAP_SWEET", "AMPLITUDE_ACTIVE"]}, {"code": "000012", "full_code": "sz000012", "name": "南  玻Ａ", "price": 4.69, "pct_chg": -2.29, "change": -0.11, "volume": 1154890.0, "amount": 545443374.73, "amplitude": 7.71, "turnover": 5.89, "pe": -36.16, "volume_ratio": 0.92, "high": 4.94, "low": 4.57, "open": 4.73, "prev_close": 4.8, "total_mv": 14269178724.0, "float_mv": 9189194845.0, "pb": 1.09, "cloud_score": 4, "cloud_signals": ["TURNOVER_OK", "CAP_SWEET", "AMPLITUDE_ACTIVE"]}, {"code": "000021", "full_code": "sz000021", "name": "深科技", "price": 58.86, "pct_chg": 10.0, "change": 5.35, "volume": 2396366.0, "amount": 13770298101.61, "amplitude": 6.19, "turnover": 15.22, "pe": 95.66, "volume_ratio": 1.18, "high": 58.86, "low": 55.55, "open": 56.0, "prev_close": 53.51, "total_mv": 92667405251.0, "float_mv": 92653826249.0, "pb": 7.12, "cloud_score": 4, "cloud_signals": ["TURNOVER_HIGH", "CAP_OK", "AMPLITUDE_ACTIVE"]}, {"code": "000037", "full_code": "sz000037", "name": "深南电A", "price": 8.87, "pct_chg": 0.0, "change": 0.0, "volume": 209835.0, "amount": 184292487.0, "amplitude": 5.52, "turnover": 6.19, "pe": 111.15, "volume_ratio": 0.79, "high": 8.99, "low": 8.5, "open": 8.8, "prev_close": 8.87, "total_mv": 5346504227.0, "float_mv": 3006115291.0, "pb": 3.2, "cloud_score": 4, "cloud_signals": ["TURNOVER_OK", "CAP_SWEET", "AMPLITUDE_ACTIVE"]}, {"code": "000048", "full_code": "sz000048", "name": "京基智农", "price": 21.21, "pct_chg": -2.39, "change": -0.52, "volume": 252256.0, "amount": 535958903.18, "amplitude": 8.24, "turnover": 4.77, "pe": -12.17, "volume_ratio": 0.7, "high": 22.3, "low": 20.51, "open": 21.81, "prev_close": 21.73, "total_mv": 11245600328.0, "float_mv": 11226511328.0, "pb": 2.99, "cloud_score": 4, "cloud_signals": ["TURNOVER_OK", "CAP_SWEET", "AMPLITUDE_ACTIVE"]}, {"code": "000060", "full_code": "sz000060", "name": "中金岭南", "price": 7.82, "pct_chg": 1.82, "change": 0.14, "volume": 2636690.0, "amount": 2076739519.82, "amplitude": 5.34, "turnover": 5.94, "pe": 17.24, "volume_ratio": 0.71, "high": 8.07, "low": 7.66, "open": 7.71, "prev_close": 7.68, "total_mv": 34729968622.0, "float_mv": 34729528747.0, "pb": 1.74, "cloud_score": 4, "cloud_signals": ["MOMENTUM_WEAK", "TURNOVER_OK", "CAP_OK", "AMPLITUDE_ACTIVE"]}, {"code": "000066", "full_code": "sz000066", "name": "中国长城", "price": 18.99, "pct_chg": 2.26, "change": 0.42, "volume": 2619826.0, "amount": 4899631045.68, "amplitude": 7.27, "turnover": 8.12, "pe": -183.15, "volume_ratio": 0.84, "high": 19.35, "low": 18.0, "open": 18.57, "prev_close": 18.57, "total_mv": 61257924681.0, "float_mv": 61253191424.0, "pb": 5.6, "cloud_score": 4, "cloud_signals": ["MOMENTUM_WEAK", "TURNOVER_OK", "CAP_OK", "AMPLITUDE_ACTIVE"]}, {"code": "000069", "full_code": "sz000069", "name": "华侨城Ａ", "price": 1.66, "pct_chg": 1.84, "change": 0.03, "volume": 596661.0, "amount": 96872099.18, "amplitude": 6.13, "turnover": 0.86, "pe": -2.44, "volume_ratio": 1.11, "high": 1.67, "low": 1.57, "open": 1.63, "prev_close": 1.63, "total_mv": 13342678368.0, "float_mv": 11451678956.0, "pb": 0.39, "cloud_score": 4, "cloud_signals": ["MOMENTUM_WEAK", "CAP_SWEET", "AMPLITUDE_ACTIVE"]}, {"code": "000151", "full_code": "sz000151", "name": "中成股份", "price": 10.8, "pct_chg": -1.73, "change": -0.19, "volume": 111603.0, "amount": 120024396.37, "amplitude": 5.73, "turnover": 3.62, "pe": 56.48, "volume_ratio": 0.65, "high": 11.11, "low": 10.48, "open": 11.04, "prev_close": 10.99, "total_mv": 3789787889.0, "float_mv": 3325694706.0, "pb": 4.33, "cloud_score": 4, "cloud_signals": ["TURNOVER_OK", "CAP_SWEET", "AMPLITUDE_ACTIVE"]}, {"code": "000422", "full_code": "sz000422", "name": "湖北宜化", "price": 13.58, "pct_chg": 2.41, "change": 0.32, "volume": 379943.0, "amount": 520265396.89, "amplitude": 3.62, "turnover": 3.59, "pe": 20.38, "volume_ratio": 0.73, "high": 13.99, "low": 13.51, "open": 13.53, "prev_close": 13.26, "total_mv": 14769400389.0, "float_mv": 14365694149.0, "pb": 2.48, "cloud_score": 4, "cloud_signals": ["MOMENTUM_WEAK", "TURNOVER_OK", "CAP_SWEET"]}, {"code": "000006", "full_code": "sz000006", "name": "深振业Ａ", "price": 7.33, "pct_chg": 2.23, "change": 0.16, "volume": 226755.0, "amount": 165207802.22, "amplitude": 4.6, "turnover": 1.68, "pe": 328.65, "volume_ratio": 0.8, "high": 7.41, "low": 7.08, "open": 7.17, "prev_close": 7.17, "total_mv": 9895463687.0, "float_mv": 9895388921.0, "pb": 1.84, "cloud_score": 3, "cloud_signals": ["MOMENTUM_WEAK", "CAP_SWEET"]}, {"code": "000019", "full_code": "sz000019", "name": "深粮控股", "price": 5.8, "pct_chg": 1.93, "change": 0.11, "volume": 69309.0, "amount": 39475636.46, "amplitude": 4.39, "turnover": 1.67, "pe": 25.73, "volume_ratio": 0.98, "high": 5.8, "low": 5.55, "open": 5.69, "prev_close": 5.69, "total_mv": 6684704473.0, "float_mv": 2413997161.0, "pb": 1.36, "cloud_score": 3, "cloud_signals": ["MOMENTUM_WEAK", "CAP_SWEET"]}, {"code": "000025", "full_code": "sz000025", "name": "特  力Ａ", "price": 13.32, "pct_chg": -8.01, "change": -1.16, "volume": 90744.0, "amount": 122717261.46, "amplitude": 8.56, "turnover": 2.31, "pe": 43.14, "volume_ratio": 0.91, "high": 14.36, "low": 13.12, "open": 14.36, "prev_close": 14.48, "total_mv": 5741696822.0, "float_mv": 5231807222.0, "pb": 3.09, "cloud_score": 3, "cloud_signals": ["CAP_SWEET", "AMPLITUDE_ACTIVE"]}, {"code": "000026", "full_code": "sz000026", "name": "飞亚达", "price": 19.58, "pct_chg": -0.71, "change": -0.14, "volume": 104423.0, "amount": 202866867.18, "amplitude": 5.32, "turnover": 2.86, "pe": 30.52, "volume_ratio": 0.74, "high": 20.01, "low": 18.96, "open": 19.68, "prev_close": 19.72, "total_mv": 7944859257.0, "float_mv": 7138099152.0, "pb": 2.37, "cloud_score": 3, "cloud_signals": ["CAP_SWEET", "AMPLITUDE_ACTIVE"]}, {"code": "000028", "full_code": "sz000028", "name": "国药一致", "price": 19.4, "pct_chg": 1.57, "change": 0.3, "volume": 27242.0, "amount": 52533525.23, "amplitude": 4.97, "turnover": 0.52, "pe": 10.33, "volume_ratio": 0.91, "high": 19.65, "low": 18.7, "open": 19.09, "prev_close": 19.1, "total_mv": 11877098730.0, "float_mv": 10201647819.0, "pb": 0.64, "cloud_score": 3, "cloud_signals": ["MOMENTUM_WEAK", "CAP_SWEET"]}, {"code": "000029", "full_code": "sz000029", "name": "深深房Ａ", "price": 22.06, "pct_chg": -5.48, "change": -1.28, "volume": 112309.0, "amount": 255754958.28, "amplitude": 9.85, "turnover": 1.26, "pe": -1420.79, "volume_ratio": 1.04, "high": 24.33, "low": 22.03, "open": 24.2, "prev_close": 23.34, "total_mv": 22317219600.0, "float_mv": 19670019600.0, "pb": 6.24, "cloud_score": 3, "cloud_signals": ["CAP_SWEET", "AMPLITUDE_ACTIVE"]}, {"code": "000031", "full_code": "sz000031", "name": "大悦城", "price": 2.16, "pct_chg": -0.46, "change": -0.01, "volume": 334342.0, "amount": 71910698.0, "amplitude": 5.53, "turnover": 0.78, "pe": -10.47, "volume_ratio": 0.84, "high": 2.2, "low": 2.08, "open": 2.18, "prev_close": 2.17, "total_mv": 9258436812.0, "float_mv": 9258418154.0, "pb": 0.91, "cloud_score": 3, "cloud_signals": ["CAP_SWEET", "AMPLITUDE_ACTIVE"]}, {"code": "000032", "full_code": "sz000032", "name": "深桑达Ａ", "price": 24.08, "pct_chg": -0.58, "change": -0.14, "volume": 856146.0, "amount": 2033198278.13, "amplitude": 11.68, "turnover": 7.52, "pe": -88.77, "volume_ratio": 0.91, "high": 25.22, "low": 22.39, "open": 24.98, "prev_close": 24.22, "total_mv": 29261517809.0, "float_mv": 27402058355.0, "pb": 3.98, "cloud_score": 3, "cloud_signals": ["TURNOVER_OK", "CAP_OK", "AMPLITUDE_ACTIVE"]}, {"code": "000034", "full_code": "sz000034", "name": "神州数码", "price": 25.81, "pct_chg": -3.04, "change": -0.81, "volume": 403100.0, "amount": 1050637566.89, "amplitude": 6.16, "turnover": 4.75, "pe": 27.8, "volume_ratio": 0.89, "high": 26.98, "low": 25.34, "open": 26.63, "prev_close": 26.62, "total_mv": 26242050702.0, "float_mv": 21916505802.0, "pb": 2.35, "cloud_score": 3, "cloud_signals": ["TURNOVER_OK", "CAP_OK", "AMPLITUDE_ACTIVE"]}, {"code": "000042", "full_code": "sz000042", "name": "中洲控股", "price": 8.21, "pct_chg": -1.56, "change": -0.13, "volume": 106021.0, "amount": 85374279.12, "amplitude": 7.67, "turnover": 1.6, "pe": -20.6, "volume_ratio": 0.98, "high": 8.46, "low": 7.82, "open": 8.36, "prev_close": 8.34, "total_mv": 5458263651.0, "float_mv": 5452281336.0, "pb": 2.41, "cloud_score": 3, "cloud_signals": ["CAP_SWEET", "AMPLITUDE_ACTIVE"]}, {"code": "000050", "full_code": "sz000050", "name": "深天马Ａ", "price": 9.48, "pct_chg": -4.05, "change": -0.4, "volume": 1096657.0, "amount": 1054622971.88, "amplitude": 8.91, "turnover": 4.5, "pe": -41.47, "volume_ratio": 0.74, "high": 10.13, "low": 9.25, "open": 9.96, "prev_close": 9.88, "total_mv": 23091152679.0, "float_mv": 23090971374.0, "pb": 0.85, "cloud_score": 3, "cloud_signals": ["TURNOVER_OK", "CAP_OK", "AMPLITUDE_ACTIVE"]}, {"code": "000062", "full_code": "sz000062", "name": "深圳华强", "price": 29.7, "pct_chg": -3.48, "change": -1.07, "volume": 434286.0, "amount": 1301222381.31, "amplitude": 7.12, "turnover": 4.16, "pe": 38.66, "volume_ratio": 0.66, "high": 31.27, "low": 29.08, "open": 30.54, "prev_close": 30.77, "total_mv": 31063506863.0, "float_mv": 31033532287.0, "pb": 4.59, "cloud_score": 3, "cloud_signals": ["TURNOVER_OK", "CAP_OK", "AMPLITUDE_ACTIVE"]}, {"code": "000068", "full_code": "sz000068", "name": "华控赛格", "price": 2.81, "pct_chg": -0.71, "change": -0.02, "volume": 183142.0, "amount": 51467589.0, "amplitude": 6.01, "turnover": 1.82, "pe": -38.93, "volume_ratio": 0.62, "high": 2.91, "low": 2.74, "open": 2.8, "prev_close": 2.83, "total_mv": 2828746814.0, "float_mv": 2828746814.0, "pb": 4.83, "cloud_score": 3, "cloud_signals": ["CAP_SWEET", "AMPLITUDE_ACTIVE"]}, {"code": "000333", "full_code": "sz000333", "name": "美的集团", "price": 77.27, "pct_chg": 3.26, "change": 2.44, "volume": 743258.0, "amount": 5697834978.37, "amplitude": 3.81, "turnover": 1.08, "pe": 11.6, "volume_ratio": 1.94, "high": 77.99, "low": 75.14, "open": 75.79, "prev_close": 74.83, "total_mv": 588290424344.0, "float_mv": 530245552000.0, "pb": 2.85, "cloud_score": 3, "cloud_signals": ["MOMENTUM_OK", "VOL_EXPAND"]}, {"code": "000338", "full_code": "sz000338", "name": "潍柴动力", "price": 26.19, "pct_chg": -6.3, "change": -1.76, "volume": 1569532.0, "amount": 4127797021.56, "amplitude": 7.48, "turnover": 3.17, "pe": 18.38, "volume_ratio": 1.47, "high": 27.87, "low": 25.78, "open": 27.6, "prev_close": 27.95, "total_mv": 226861567624.0, "float_mv": 129725183322.0, "pb": 2.38, "cloud_score": 3, "cloud_signals": ["TURNOVER_OK", "VOL_EXPAND", "AMPLITUDE_ACTIVE"]}, {"code": "000410", "full_code": "sz000410", "name": "沈阳机床", "price": 4.58, "pct_chg": 0.44, "change": 0.02, "volume": 252539.0, "amount": 114187649.42, "amplitude": 5.04, "turnover": 1.28, "pe": -89.65, "volume_ratio": 1.03, "high": 4.61, "low": 4.38, "open": 4.52, "prev_close": 4.56, "total_mv": 12132754381.0, "float_mv": 9027263965.0, "pb": 2.9, "cloud_score": 3, "cloud_signals": ["CAP_SWEET", "AMPLITUDE_ACTIVE"]}, {"code": "000419", "full_code": "sz000419", "name": "通程控股", "price": 4.59, "pct_chg": 1.1, "change": 0.05, "volume": 65094.0, "amount": 29609102.51, "amplitude": 4.63, "turnover": 1.2, "pe": 22.23, "volume_ratio": 0.84, "high": 4.63, "low": 4.42, "open": 4.52, "prev_close": 4.54, "total_mv": 2495044386.0, "float_mv": 2495044386.0, "pb": 0.73, "cloud_score": 3, "cloud_signals": ["MOMENTUM_WEAK", "CAP_SWEET"]}, {"code": "000421", "full_code": "sz000421", "name": "南京公用", "price": 5.03, "pct_chg": -0.4, "change": -0.02, "volume": 74462.0, "amount": 37191718.0, "amplitude": 4.16, "turnover": 1.3, "pe": 9.98, "volume_ratio": 1.27, "high": 5.08, "low": 4.87, "open": 5.05, "prev_close": 5.05, "total_mv": 2889311142.0, "float_mv": 2888710374.0, "pb": 1.04, "cloud_score": 3, "cloud_signals": ["VOL_EXPAND", "CAP_SWEET"]}, {"code": "000002", "full_code": "sz000002", "name": "万  科Ａ", "price": 3.04, "pct_chg": 1.0, "change": 0.03, "volume": 1558535.0, "amount": 470554213.62, "amplitude": 4.98, "turnover": 1.6, "pe": -1.52, "volume_ratio": 0.95, "high": 3.09, "low": 2.94, "open": 2.96, "prev_close": 3.01, "total_mv": 36269356792.0, "float_mv": 29539485030.0, "pb": 0.33, "cloud_score": 2, "cloud_signals": ["MOMENTUM_WEAK", "CAP_OK"]}, {"code": "000007", "full_code": "sz000007", "name": "全新好", "price": 12.29, "pct_chg": -2.92, "change": -0.37, "volume": 59304.0, "amount": 73377780.0, "amplitude": 4.58, "turnover": 1.71, "pe": -490.38, "volume_ratio": 0.7, "high": 12.78, "low": 12.2, "open": 12.63, "prev_close": 12.66, "total_mv": 4257846461.0, "float_mv": 4257846461.0, "pb": 23.77, "cloud_score": 2, "cloud_signals": ["CAP_SWEET"]}, {"code": "000009", "full_code": "sz000009", "name": "中国宝安", "price": 6.14, "pct_chg": -0.81, "change": -0.05, "volume": 310222.0, "amount": 189589383.9, "amplitude": 4.52, "turnover": 1.2, "pe": 226.72, "volume_ratio": 1.17, "high": 6.21, "low": 5.93, "open": 6.17, "prev_close": 6.19, "total_mv": 15836373745.0, "float_mv": 15816765655.0, "pb": 1.58, "cloud_score": 2, "cloud_signals": ["CAP_SWEET"]}, {"code": "000011", "full_code": "sz000011", "name": "深物业A", "price": 6.58, "pct_chg": -0.75, "change": -0.05, "volume": 36384.0, "amount": 23967735.86, "amplitude": 3.17, "turnover": 0.69, "pe": -36.0, "volume_ratio": 0.64, "high": 6.68, "low": 6.47, "open": 6.63, "prev_close": 6.63, "total_mv": 3921542425.0, "float_mv": 3464209073.0, "pb": 1.17, "cloud_score": 2, "cloud_signals": ["CAP_SWEET"]}, {"code": "000014", "full_code": "sz000014", "name": "沙河股份", "price": 9.18, "pct_chg": -1.08, "change": -0.1, "volume": 54148.0, "amount": 49574028.6, "amplitude": 3.56, "turnover": 2.24, "pe": -65.44, "volume_ratio": 0.78, "high": 9.3, "low": 8.97, "open": 9.27, "prev_close": 9.28, "total_mv": 2221984336.0, "float_mv": 2221984336.0, "pb": 1.61, "cloud_score": 2, "cloud_signals": ["CAP_SWEET"]}, {"code": "000020", "full_code": "sz000020", "name": "深华发Ａ", "price": 10.76, "pct_chg": -0.83, "change": -0.09, "volume": 43758.0, "amount": 46804254.0, "amplitude": 4.15, "turnover": 2.42, "pe": 146.39, "volume_ratio": 0.99, "high": 10.88, "low": 10.43, "open": 10.79, "prev_close": 10.85, "total_mv": 3046814803.0, "float_mv": 1949339607.0, "pb": 6.86, "cloud_score": 2, "cloud_signals": ["CAP_SWEET"]}, {"code": "000030", "full_code": "sz000030", "name": "富奥股份", "price": 3.92, "pct_chg": -0.25, "change": -0.01, "volume": 97523.0, "amount": 37948385.88, "amplitude": 3.56, "turnover": 0.58, "pe": 13.52, "volume_ratio": 1.05, "high": 3.95, "low": 3.81, "open": 3.92, "prev_close": 3.93, "total_mv": 6741658512.0, "float_mv": 6549951794.0, "pb": 0.81, "cloud_score": 2, "cloud_signals": ["CAP_SWEET"]}, {"code": "000035", "full_code": "sz000035", "name": "中国天楹", "price": 4.88, "pct_chg": -1.41, "change": -0.07, "volume": 354737.0, "amount": 172927897.36, "amplitude": 3.43, "turnover": 1.53, "pe": 26.31, "volume_ratio": 0.95, "high": 4.94, "low": 4.77, "open": 4.9, "prev_close": 4.95, "total_mv": 11653599913.0, "float_mv": 11287565650.0, "pb": 1.08, "cloud_score": 2, "cloud_signals": ["CAP_SWEET"]}, {"code": "000036", "full_code": "sz000036", "name": "华联控股", "price": 4.47, "pct_chg": -0.22, "change": -0.01, "volume": 232776.0, "amount": 103672461.75, "amplitude": 4.69, "turnover": 1.66, "pe": 60.25, "volume_ratio": 0.95, "high": 4.55, "low": 4.34, "open": 4.46, "prev_close": 4.48, "total_mv": 6275069701.0, "float_mv": 6271326103.0, "pb": 1.22, "cloud_score": 2, "cloud_signals": ["CAP_SWEET"]}, {"code": "000039", "full_code": "sz000039", "name": "中集集团", "price": 8.19, "pct_chg": -2.85, "change": -0.24, "volume": 435120.0, "amount": 354747342.91, "amplitude": 4.74, "turnover": 1.89, "pe": 52.84, "volume_ratio": 0.86, "high": 8.4, "low": 8.0, "open": 8.39, "prev_close": 8.43, "total_mv": 44164741953.0, "float_mv": 18848524485.0, "pb": 0.95, "cloud_score": 2, "cloud_signals": ["CAP_SWEET"]}, {"code": "000045", "full_code": "sz000045", "name": "深纺织Ａ", "price": 9.95, "pct_chg": -0.5, "change": -0.05, "volume": 73384.0, "amount": 72885154.0, "amplitude": 3.4, "turnover": 1.61, "pe": 56.73, "volume_ratio": 1.0, "high": 10.13, "low": 9.79, "open": 9.91, "prev_close": 10.0, "total_mv": 5039892398.0, "float_mv": 4547367398.0, "pb": 1.69, "cloud_score": 2, "cloud_signals": ["CAP_SWEET"]}, {"code": "000049", "full_code": "sz000049", "name": "德赛电池", "price": 22.82, "pct_chg": -1.21, "change": -0.28, "volume": 77897.0, "amount": 177094216.69, "amplitude": 3.33, "turnover": 2.03, "pe": 27.46, "volume_ratio": 0.84, "high": 23.12, "low": 22.35, "open": 22.9, "prev_close": 23.1, "total_mv": 8777451346.0, "float_mv": 8775085551.0, "pb": 1.31, "cloud_score": 2, "cloud_signals": ["CAP_SWEET"]}, {"code": "000055", "full_code": "sz000055", "name": "方大集团", "price": 3.33, "pct_chg": -0.89, "change": -0.03, "volume": 147417.0, "amount": 48863092.89, "amplitude": 4.76, "turnover": 2.18, "pe": 31.7, "volume_ratio": 0.84, "high": 3.39, "low": 3.23, "open": 3.32, "prev_close": 3.36, "total_mv": 3576001176.0, "float_mv": 2250595249.0, "pb": 0.64, "cloud_score": 2, "cloud_signals": ["CAP_SWEET"]}, {"code": "000058", "full_code": "sz000058", "name": "深 赛 格", "price": 6.1, "pct_chg": -0.49, "change": -0.03, "volume": 85986.0, "amount": 52138548.63, "amplitude": 3.59, "turnover": 0.87, "pe": 75.99, "volume_ratio": 1.1, "high": 6.15, "low": 5.93, "open": 6.13, "prev_close": 6.13, "total_mv": 7510324099.0, "float_mv": 6006910059.0, "pb": 3.74, "cloud_score": 2, "cloud_signals": ["CAP_SWEET"]}, {"code": "000059", "full_code": "sz000059", "name": "华锦股份", "price": 3.82, "pct_chg": -0.26, "change": -0.01, "volume": 255947.0, "amount": 96969554.18, "amplitude": 4.18, "turnover": 1.6, "pe": 34.44, "volume_ratio": 1.06, "high": 3.85, "low": 3.69, "open": 3.82, "prev_close": 3.83, "total_mv": 6109870491.0, "float_mv": 6109757610.0, "pb": 0.63, "cloud_score": 2, "cloud_signals": ["CAP_SWEET"]}, {"code": "000065", "full_code": "sz000065", "name": "北方国际", "price": 10.01, "pct_chg": -3.75, "change": -0.39, "volume": 207887.0, "amount": 208529651.08, "amplitude": 3.75, "turnover": 2.13, "pe": 26.31, "volume_ratio": 0.71, "high": 10.22, "low": 9.83, "open": 10.2, "prev_close": 10.4, "total_mv": 11626036012.0, "float_mv": 9759372503.0, "pb": 1.05, "cloud_score": 2, "cloud_signals": ["CAP_SWEET"]}, {"code": "000088", "full_code": "sz000088", "name": "盐 田 港", "price": 4.08, "pct_chg": 0.0, "change": 0.0, "volume": 155432.0, "amount": 62711379.0, "amplitude": 2.7, "turnover": 0.49, "pe": 15.57, "volume_ratio": 0.88, "high": 4.09, "low": 3.98, "open": 4.07, "prev_close": 4.08, "total_mv": 21213892052.0, "float_mv": 12904573697.0, "pb": 1.19, "cloud_score": 2, "cloud_signals": ["CAP_SWEET"]}, {"code": "000089", "full_code": "sz000089", "name": "深圳机场", "price": 6.14, "pct_chg": 0.16, "change": 0.01, "volume": 135988.0, "amount": 82954605.0, "amplitude": 4.08, "turnover": 0.66, "pe": 12.19, "volume_ratio": 1.15, "high": 6.2, "low": 5.95, "open": 6.13, "prev_close": 6.13, "total_mv": 12591724785.0, "float_mv": 12591724785.0, "pb": 1.09, "cloud_score": 2, "cloud_signals": ["CAP_SWEET"]}, {"code": "000090", "full_code": "sz000090", "name": "天健集团", "price": 3.11, "pct_chg": -1.27, "change": -0.04, "volume": 214409.0, "amount": 66356684.56, "amplitude": 3.81, "turnover": 1.15, "pe": -62.31, "volume_ratio": 0.98, "high": 3.15, "low": 3.03, "open": 3.15, "prev_close": 3.15, "total_mv": 5811176300.0, "float_mv": 5810821760.0, "pb": 0.52, "cloud_score": 2, "cloud_signals": ["CAP_SWEET"]}, {"code": "000096", "full_code": "sz000096", "name": "广聚能源", "price": 7.0, "pct_chg": 0.29, "change": 0.02, "volume": 65602.0, "amount": 45560168.0, "amplitude": 3.58, "turnover": 1.28, "pe": 75.56, "volume_ratio": 0.96, "high": 7.04, "low": 6.79, "open": 6.98, "prev_close": 6.98, "total_mv": 3696000000.0, "float_mv": 3575936000.0, "pb": 1.34, "cloud_score": 2, "cloud_signals": ["CAP_SWEET"]}, {"code": "000099", "full_code": "sz000099", "name": "中信海直", "price": 14.48, "pct_chg": -4.04, "change": -0.61, "volume": 126740.0, "amount": 184134042.16, "amplitude": 3.25, "turnover": 1.63, "pe": 30.15, "volume_ratio": 0.81, "high": 14.79, "low": 14.3, "open": 14.6, "prev_close": 15.09, "total_mv": 11233151584.0, "float_mv": 11233151584.0, "pb": 2.04, "cloud_score": 2, "cloud_signals": ["CAP_SWEET"]}, {"code": "000100", "full_code": "sz000100", "name": "TCL科技", "price": 5.29, "pct_chg": -2.04, "change": -0.11, "volume": 17084609.0, "amount": 9143344961.18, "amplitude": 6.85, "turnover": 8.93, "pe": 17.67, "volume_ratio": 1.01, "high": 5.57, "low": 5.2, "open": 5.43, "prev_close": 5.4, "total_mv": 110036562345.0, "float_mv": 101208461458.0, "pb": 1.81, "cloud_score": 2, "cloud_signals": ["TURNOVER_OK", "AMPLITUDE_ACTIVE"]}, {"code": "000156", "full_code": "sz000156", "name": "华数传媒", "price": 6.43, "pct_chg": -1.23, "change": -0.08, "volume": 96559.0, "amount": 62075129.44, "amplitude": 3.23, "turnover": 0.57, "pe": 26.45, "volume_ratio": 0.93, "high": 6.55, "low": 6.34, "open": 6.5, "prev_close": 6.51, "total_mv": 11914355602.0, "float_mv": 10930201889.0, "pb": 0.78, "cloud_score": 2, "cloud_signals": ["CAP_SWEET"]}, {"code": "000157", "full_code": "sz000157", "name": "中联重科", "price": 7.21, "pct_chg": -1.37, "change": -0.1, "volume": 975777.0, "amount": 697615253.6, "amplitude": 5.2, "turnover": 1.38, "pe": 17.63, "volume_ratio": 1.18, "high": 7.31, "low": 6.93, "open": 7.25, "prev_close": 7.31, "total_mv": 62355939052.0, "float_mv": 50972317816.0, "pb": 1.07, "cloud_score": 2, "cloud_signals": ["CAP_OK", "AMPLITUDE_ACTIVE"]}, {"code": "000159", "full_code": "sz000159", "name": "国际实业", "price": 5.29, "pct_chg": -0.75, "change": -0.04, "volume": 103536.0, "amount": 54817674.88, "amplitude": 3.19, "turnover": 2.15, "pe": 87.16, "volume_ratio": 0.65, "high": 5.37, "low": 5.2, "open": 5.37, "prev_close": 5.33, "total_mv": 2542828903.0, "float_mv": 2542736328.0, "pb": 1.23, "cloud_score": 2, "cloud_signals": ["CAP_SWEET"]}, {"code": "000400", "full_code": "sz000400", "name": "许继电气", "price": 21.59, "pct_chg": 1.22, "change": 0.26, "volume": 173937.0, "amount": 371138745.56, "amplitude": 4.17, "turnover": 1.72, "pe": 49.51, "volume_ratio": 0.84, "high": 21.66, "low": 20.77, "open": 21.12, "prev_close": 21.33, "total_mv": 21992054356.0, "float_mv": 21842630182.0, "pb": 1.83, "cloud_score": 2, "cloud_signals": ["MOMENTUM_WEAK", "CAP_OK"]}, {"code": "000401", "full_code": "sz000401", "name": "金隅冀东", "price": 3.43, "pct_chg": 0.88, "change": 0.03, "volume": 109157.0, "amount": 36908456.0, "amplitude": 4.12, "turnover": 0.41, "pe": -2.29, "volume_ratio": 1.15, "high": 3.44, "low": 3.3, "open": 3.4, "prev_close": 3.4, "total_mv": 9117685298.0, "float_mv": 9025546580.0, "pb": 0.35, "cloud_score": 2, "cloud_signals": ["CAP_SWEET"]}, {"code": "000402", "full_code": "sz000402", "name": "金 融 街", "price": 2.51, "pct_chg": -1.95, "change": -0.05, "volume": 556639.0, "amount": 139917966.53, "amplitude": 2.73, "turnover": 1.86, "pe": 5.44, "volume_ratio": 1.14, "high": 2.55, "low": 2.48, "open": 2.53, "prev_close": 2.56, "total_mv": 7502214067.0, "float_mv": 7501521407.0, "pb": 0.38, "cloud_score": 2, "cloud_signals": ["CAP_SWEET"]}, {"code": "000407", "full_code": "sz000407", "name": "胜利股份", "price": 3.69, "pct_chg": -0.81, "change": -0.03, "volume": 135355.0, "amount": 49793656.76, "amplitude": 4.03, "turnover": 1.55, "pe": 22.56, "volume_ratio": 0.92, "high": 3.75, "low": 3.6, "open": 3.7, "prev_close": 3.72, "total_mv": 3247512381.0, "float_mv": 3231608872.0, "pb": 1.05, "cloud_score": 2, "cloud_signals": ["CAP_SWEET"]}, {"code": "000408", "full_code": "sz000408", "name": "藏格矿业", "price": 70.16, "pct_chg": 3.1, "change": 2.11, "volume": 132416.0, "amount": 917401697.32, "amplitude": 4.82, "turnover": 0.84, "pe": 17.49, "volume_ratio": 0.68, "high": 70.93, "low": 67.65, "open": 68.06, "prev_close": 68.05, "total_mv": 110075059141.0, "float_mv": 110073901501.0, "pb": 7.2, "cloud_score": 2, "cloud_signals": ["MOMENTUM_OK"]}, {"code": "000409", "full_code": "sz000409", "name": "云鼎科技", "price": 8.17, "pct_chg": -2.74, "change": -0.23, "volume": 58126.0, "amount": 47854050.45, "amplitude": 4.64, "turnover": 0.98, "pe": 70.07, "volume_ratio": 0.9, "high": 8.51, "low": 8.12, "open": 8.51, "prev_close": 8.4, "total_mv": 5537221626.0, "float_mv": 4824249247.0, "pb": 3.37, "cloud_score": 2, "cloud_signals": ["CAP_SWEET"]}, {"code": "000027", "full_code": "sz000027", "name": "深圳能源", "price": 6.35, "pct_chg": -0.94, "change": -0.06, "volume": 373464.0, "amount": 235370504.66, "amplitude": 3.59, "turnover": 0.79, "pe": 6.04, "volume_ratio": 0.83, "high": 6.4, "low": 6.17, "open": 6.37, "prev_close": 6.41, "total_mv": 30209425967.0, "float_mv": 30209425967.0, "pb": 0.92, "cloud_score": 1, "cloud_signals": ["CAP_OK"]}, {"code": "000155", "full_code": "sz000155", "name": "川能动力", "price": 11.89, "pct_chg": -1.0, "change": -0.12, "volume": 277085.0, "amount": 329798503.4, "amplitude": 3.58, "turnover": 1.5, "pe": 20.57, "volume_ratio": 0.78, "high": 12.1, "low": 11.67, "open": 11.99, "prev_close": 12.01, "total_mv": 21950941586.0, "float_mv": 21950941586.0, "pb": 2.04, "cloud_score": 1, "cloud_signals": ["CAP_OK"]}, {"code": "000158", "full_code": "sz000158", "name": "常山北明", "price": 12.73, "pct_chg": 0.16, "change": 0.02, "volume": 284258.0, "amount": 361202556.44, "amplitude": 4.09, "turnover": 1.79, "pe": -50.08, "volume_ratio": 0.86, "high": 13.0, "low": 12.48, "open": 12.65, "prev_close": 12.71, "total_mv": 20350390858.0, "float_mv": 20214114617.0, "pb": 3.87, "cloud_score": 1, "cloud_signals": ["CAP_OK"]}, {"code": "000166", "full_code": "sz000166", "name": "申万宏源", "price": 4.46, "pct_chg": 1.36, "change": 0.06, "volume": 1275809.0, "amount": 565641245.54, "amplitude": 2.73, "turnover": 0.57, "pe": 11.85, "volume_ratio": 0.71, "high": 4.48, "low": 4.36, "open": 4.4, "prev_close": 4.4, "total_mv": 111678152738.0, "float_mv": 100508362629.0, "pb": 0.97, "cloud_score": 1, "cloud_signals": ["MOMENTUM_WEAK"]}, {"code": "000301", "full_code": "sz000301", "name": "东方盛虹", "price": 11.3, "pct_chg": -0.79, "change": -0.09, "volume": 244597.0, "amount": 276176098.51, "amplitude": 4.57, "turnover": 0.37, "pe": 13.04, "volume_ratio": 0.99, "high": 11.52, "low": 11.0, "open": 11.24, "prev_close": 11.39, "total_mv": 74706925216.0, "float_mv": 74671844976.0, "pb": 2.15, "cloud_score": 1, "cloud_signals": ["CAP_OK"]}, {"code": "000415", "full_code": "sz000415", "name": "渤海租赁", "price": 4.11, "pct_chg": -1.2, "change": -0.05, "volume": 707899.0, "amount": 287564896.0, "amplitude": 4.33, "turnover": 1.31, "pe": 7.0, "volume_ratio": 1.0, "high": 4.17, "low": 3.99, "open": 4.16, "prev_close": 4.16, "total_mv": 25418382469.0, "float_mv": 22164876059.0, "pb": 0.85, "cloud_score": 1, "cloud_signals": ["CAP_OK"]}, {"code": "000001", "full_code": "sz000001", "name": "平安银行", "price": 10.24, "pct_chg": 0.1, "change": 0.01, "volume": 1124140.0, "amount": 1144166877.64, "amplitude": 2.93, "turnover": 0.58, "pe": 3.42, "volume_ratio": 0.95, "high": 10.32, "low": 10.02, "open": 10.22, "prev_close": 10.23, "total_mv": 198716602348.0, "float_mv": 198713350687.0, "pb": 0.43, "cloud_score": 0, "cloud_signals": []}, {"code": "000063", "full_code": "sz000063", "name": "中兴通讯", "price": 35.2, "pct_chg": -1.32, "change": -0.47, "volume": 1179960.0, "amount": 4156144513.59, "amplitude": 4.07, "turnover": 2.93, "pe": 32.12, "volume_ratio": 0.52, "high": 36.18, "low": 34.73, "open": 35.35, "prev_close": 35.67, "total_mv": 168380428022.0, "float_mv": 141772267366.0, "pb": 2.2, "cloud_score": 0, "cloud_signals": []}], "indices": [{"code": "000001", "name": "上证指数", "price": 4073.9, "pct_chg": 1.16, "change": 46.64, "amount": 1666220369467.3}, {"code": "399001", "name": "深证成指", "price": 15812.87, "pct_chg": 0.19, "change": 30.65, "amount": 1851533399374.03}, {"code": "399006", "name": "创业板指", "price": 4216.7, "pct_chg": 0.54, "change": 22.49, "amount": 921211835851.52}, {"code": "000016", "name": "*ST康佳A", "price": 2.19, "pct_chg": -5.19, "change": -0.12, "amount": 64348391.26}, {"code": "000688", "name": "国城矿业", "price": 33.42, "pct_chg": 3.6, "change": 1.16, "amount": 1086828044.07}], "total_count": 5534}, "lhb": {"timestamp": "2026-06-29T11:33:53.083955", "date": "20260629", "entries": []}, "sectors": {"timestamp": "2026-06-29T11:33:53.084007", "sectors": [{"code": "BK0420", "name": "航空机场", "pct_chg": -1.06, "turnover": 0.92, "amount": null}, {"code": "BK0421", "name": "铁路公路", "pct_chg": 0.33, "turnover": 0.57, "amount": null}, {"code": "BK0422", "name": "物流", "pct_chg": 0.1, "turnover": 1.11, "amount": null}, {"code": "BK0424", "name": "水泥", "pct_chg": -0.74, "turnover": 1.15, "amount": null}, {"code": "BK0427", "name": "公用事业", "pct_chg": -0.26, "turnover": 1.68, "amount": null}, {"code": "BK0428", "name": "电力", "pct_chg": -0.16, "turnover": 1.67, "amount": null}, {"code": "BK0433", "name": "农林牧渔", "pct_chg": 1.63, "turnover": 2.34, "amount": null}, {"code": "BK0436", "name": "纺织服饰", "pct_chg": 0.12, "turnover": 2.02, "amount": null}, {"code": "BK0437", "name": "煤炭", "pct_chg": 1.22, "turnover": 1.01, "amount": null}, {"code": "BK0438", "name": "食品饮料", "pct_chg": 0.91, "turnover": 1.89, "amount": null}, {"code": "BK0440", "name": "家居用品", "pct_chg": 0.08, "turnover": 2.3, "amount": null}, {"code": "BK0448", "name": "通信设备", "pct_chg": -2.93, "turnover": 5.04, "amount": null}, {"code": "BK0450", "name": "航运港口", "pct_chg": -0.61, "turnover": 0.88, "amount": null}, {"code": "BK0451", "name": "房地产开发", "pct_chg": -0.76, "turnover": 2.01, "amount": null}, {"code": "BK0454", "name": "塑料", "pct_chg": -1.99, "turnover": 5.38, "amount": null}, {"code": "BK0456", "name": "家用电器", "pct_chg": 1.01, "turnover": 2.32, "amount": null}, {"code": "BK0457", "name": "电网设备", "pct_chg": -0.78, "turnover": 2.97, "amount": null}, {"code": "BK0458", "name": "仪器仪表", "pct_chg": -0.63, "turnover": 3.52, "amount": null}, {"code": "BK0459", "name": "元件", "pct_chg": -3.69, "turnover": 7.79, "amount": null}, {"code": "BK0464", "name": "石油石化", "pct_chg": -0.61, "turnover": 0.52, "amount": null}, {"code": "BK0465", "name": "化学制药", "pct_chg": 5.87, "turnover": 3.29, "amount": null}, {"code": "BK0471", "name": "化学纤维", "pct_chg": -0.82, "turnover": 3.47, "amount": null}, {"code": "BK0473", "name": "证券Ⅱ", "pct_chg": 0.51, "turnover": 1.68, "amount": null}, {"code": "BK0474", "name": "保险Ⅱ", "pct_chg": 2.19, "turnover": 0.45, "amount": null}, {"code": "BK0475", "name": "银行Ⅱ", "pct_chg": 0.1, "turnover": 0.31, "amount": null}, {"code": "BK0476", "name": "装修建材", "pct_chg": -1.13, "turnover": 2.54, "amount": null}, {"code": "BK0478", "name": "有色金属", "pct_chg": -0.16, "turnover": 3.59, "amount": null}, {"code": "BK0479", "name": "钢铁", "pct_chg": 0.27, "turnover": 1.33, "amount": null}, {"code": "BK0481", "name": "汽车零部件", "pct_chg": -1.16, "turnover": 2.43, "amount": null}, {"code": "BK0482", "name": "一般零售", "pct_chg": 1.05, "turnover": 1.92, "amount": null}, {"code": "BK0484", "name": "贸易Ⅱ", "pct_chg": -0.81, "turnover": 1.8, "amount": null}, {"code": "BK0486", "name": "传媒", "pct_chg": -0.07, "turnover": 2.92, "amount": null}, {"code": "BK0538", "name": "化学制品", "pct_chg": -0.6, "turnover": 3.9, "amount": null}, {"code": "BK0539", "name": "综合Ⅱ", "pct_chg": -1.33, "turnover": 2.11, "amount": null}, {"code": "BK0545", "name": "通用设备", "pct_chg": -0.99, "turnover": 4.6, "amount": null}, {"code": "BK0546", "name": "玻璃玻纤", "pct_chg": -3.94, "turnover": 5.67, "amount": null}, {"code": "BK0725", "name": "装修装饰Ⅱ", "pct_chg": -0.92, "turnover": 3.22, "amount": null}, {"code": "BK0726", "name": "工程咨询服务Ⅱ", "pct_chg": 0.0, "turnover": 5.36, "amount": null}, {"code": "BK0727", "name": "医疗服务", "pct_chg": 6.1, "turnover": 3.46, "amount": null}, {"code": "BK0728", "name": "环保", "pct_chg": -0.39, "turnover": 2.25, "amount": null}, {"code": "BK0731", "name": "农化制品", "pct_chg": -0.63, "turnover": 2.53, "amount": null}, {"code": "BK0732", "name": "贵金属", "pct_chg": 1.17, "turnover": 2.61, "amount": null}, {"code": "BK0734", "name": "饰品", "pct_chg": 2.12, "turnover": 1.56, "amount": null}, {"code": "BK0735", "name": "计算机设备", "pct_chg": -0.99, "turnover": 3.03, "amount": null}, {"code": "BK0736", "name": "通信服务", "pct_chg": -2.12, "turnover": 0.83, "amount": null}, {"code": "BK0737", "name": "软件开发", "pct_chg": -0.32, "turnover": 2.45, "amount": null}, {"code": "BK0738", "name": "多元金融", "pct_chg": 0.05, "turnover": 0.97, "amount": null}, {"code": "BK0739", "name": "工程机械", "pct_chg": -0.64, "turnover": 1.65, "amount": null}, {"code": "BK0740", "name": "教育", "pct_chg": -0.04, "turnover": 2.67, "amount": null}, {"code": "BK0910", "name": "专用设备", "pct_chg": -0.88, "turnover": 3.08, "amount": null}, {"code": "BK1015", "name": "能源金属", "pct_chg": 0.97, "turnover": 5.45, "amount": null}, {"code": "BK1016", "name": "汽车服务", "pct_chg": -1.52, "turnover": 1.62, "amount": null}, {"code": "BK1018", "name": "橡胶", "pct_chg": -0.66, "turnover": 4.92, "amount": null}, {"code": "BK1019", "name": "化学原料", "pct_chg": -0.55, "turnover": 2.31, "amount": null}, {"code": "BK1020", "name": "非金属材料Ⅱ", "pct_chg": -4.52, "turnover": 5.35, "amount": null}, {"code": "BK1027", "name": "小金属", "pct_chg": 0.27, "turnover": 6.62, "amount": null}, {"code": "BK1028", "name": "燃气Ⅱ", "pct_chg": -0.63, "turnover": 1.81, "amount": null}, {"code": "BK1030", "name": "电机Ⅱ", "pct_chg": -2.05, "turnover": 3.02, "amount": null}, {"code": "BK1031", "name": "光伏设备", "pct_chg": -0.01, "turnover": 3.53, "amount": null}, {"code": "BK1032", "name": "风电设备", "pct_chg": -1.02, "turnover": 3.38, "amount": null}, {"code": "BK1033", "name": "电池", "pct_chg": -1.02, "turnover": 4.13, "amount": null}, {"code": "BK1034", "name": "其他电源设备Ⅱ", "pct_chg": -0.27, "turnover": 2.79, "amount": null}, {"code": "BK1035", "name": "美容护理", "pct_chg": 2.07, "turnover": 1.85, "amount": null}, {"code": "BK1036", "name": "半导体", "pct_chg": 2.76, "turnover": 8.13, "amount": null}, {"code": "BK1037", "name": "消费电子", "pct_chg": -3.2, "turnover": 3.71, "amount": null}, {"code": "BK1038", "name": "光学光电子", "pct_chg": -1.9, "turnover": 8.42, "amount": null}, {"code": "BK1039", "name": "电子化学品Ⅱ", "pct_chg": 1.8, "turnover": 13.83, "amount": null}, {"code": "BK1040", "name": "中药Ⅱ", "pct_chg": 3.81, "turnover": 2.03, "amount": null}, {"code": "BK1041", "name": "医疗器械", "pct_chg": 3.55, "turnover": 2.46, "amount": null}, {"code": "BK1042", "name": "医药商业", "pct_chg": 2.36, "turnover": 1.65, "amount": null}, {"code": "BK1043", "name": "专业服务", "pct_chg": -1.83, "turnover": 2.32, "amount": null}, {"code": "BK1044", "name": "生物制品", "pct_chg": 7.29, "turnover": 2.51, "amount": null}, {"code": "BK1045", "name": "房地产服务", "pct_chg": 0.84, "turnover": 2.17, "amount": null}, {"code": "BK1046", "name": "游戏Ⅱ", "pct_chg": 2.07, "turnover": 3.51, "amount": null}, {"code": "BK1200", "name": "电力设备", "pct_chg": -0.77, "turnover": 3.38, "amount": null}, {"code": "BK1201", "name": "电子", "pct_chg": -0.5, "turnover": 7.36, "amount": null}, {"code": "BK1202", "name": "房地产", "pct_chg": -0.55, "turnover": 2.02, "amount": null}, {"code": "BK1203", "name": "非银金融", "pct_chg": 0.46, "turnover": 1.33, "amount": null}, {"code": "BK1204", "name": "国防军工", "pct_chg": -1.27, "turnover": 2.86, "amount": null}, {"code": "BK1205", "name": "机械设备", "pct_chg": -0.94, "turnover": 3.18, "amount": null}, {"code": "BK1206", "name": "基础化工", "pct_chg": -0.98, "turnover": 3.34, "amount": null}, {"code": "BK1207", "name": "计算机", "pct_chg": -0.91, "turnover": 2.89, "amount": null}, {"code": "BK1208", "name": "建筑材料", "pct_chg": -1.63, "turnover": 2.71, "amount": null}, {"code": "BK1209", "name": "建筑装饰", "pct_chg": -0.38, "turnover": 1.66, "amount": null}, {"code": "BK1210", "name": "交通运输", "pct_chg": -0.16, "turnover": 0.83, "amount": null}, {"code": "BK1211", "name": "汽车", "pct_chg": -0.9, "turnover": 2.02, "amount": null}, {"code": "BK1212", "name": "轻工制造", "pct_chg": 0.08, "turnover": 2.59, "amount": null}, {"code": "BK1213", "name": "商贸零售", "pct_chg": 0.44, "turnover": 1.9, "amount": null}, {"code": "BK1214", "name": "社会服务", "pct_chg": -0.47, "turnover": 2.3, "amount": null}, {"code": "BK1215", "name": "通信", "pct_chg": -2.68, "turnover": 1.96, "amount": null}, {"code": "BK1216", "name": "医药生物", "pct_chg": 4.94, "turnover": 2.71, "amount": null}, {"code": "BK1217", "name": "综合", "pct_chg": -1.33, "turnover": 2.11, "amount": null}, {"code": "BK1218", "name": "出版", "pct_chg": -0.05, "turnover": 0.84, "amount": null}, {"code": "BK1219", "name": "电视广播Ⅱ", "pct_chg": -1.73, "turnover": 1.5, "amount": null}, {"code": "BK1220", "name": "广告营销", "pct_chg": -0.63, "turnover": 4.25, "amount": null}, {"code": "BK1221", "name": "数字媒体", "pct_chg": -0.92, "turnover": 4.88, "amount": null}, {"code": "BK1222", "name": "影视院线", "pct_chg": -0.11, "turnover": 3.23, "amount": null}, {"code": "BK1223", "name": "其他电子Ⅱ", "pct_chg": -1.99, "turnover": 6.23, "amount": null}, {"code": "BK1224", "name": "纺织制造", "pct_chg": -0.12, "turnover": 2.22, "amount": null}, {"code": "BK1225", "name": "服装家纺", "pct_chg": -0.31, "turnover": 2.06, "amount": null}]}, "candidates": [{"code": "000404", "full_code": "sz000404", "name": "长虹华意", "price": 8.06, "pct_chg": 8.77, "change": 0.65, "volume": 431147.0, "amount": 344061504.81, "amplitude": 6.07, "turnover": 6.22, "pe": 12.16, "volume_ratio": 3.7, "high": 8.15, "low": 7.7, "open": 7.7, "prev_close": 7.41, "total_mv": 5609727591.0, "float_mv": 5583389671.0, "pb": 1.34, "cloud_score": 8, "cloud_signals": ["MOMENTUM_OK", "TURNOVER_OK", "VOL_BOOM", "CAP_SWEET", "AMPLITUDE_ACTIVE"]}, {"code": "000417", "full_code": "sz000417", "name": "合百集团", "price": 8.6, "pct_chg": 6.04, "change": 0.49, "volume": 1105108.0, "amount": 929297635.55, "amplitude": 7.4, "turnover": 14.19, "pe": 26.08, "volume_ratio": 1.32, "high": 8.66, "low": 8.06, "open": 8.09, "prev_close": 8.11, "total_mv": 6707004120.0, "float_mv": 6699636079.0, "pb": 1.41, "cloud_score": 8, "cloud_signals": ["MOMENTUM_OK", "TURNOVER_HIGH", "VOL_EXPAND", "CAP_SWEET", "AMPLITUDE_ACTIVE"]}, {"code": "000420", "full_code": "sz000420", "name": "吉林化纤", "price": 4.2, "pct_chg": 4.22, "change": 0.17, "volume": 1592950.0, "amount": 678090503.41, "amplitude": 7.94, "turnover": 6.48, "pe": 94.75, "volume_ratio": 2.04, "high": 4.43, "low": 4.11, "open": 4.16, "prev_close": 4.03, "total_mv": 10327247041.0, "float_mv": 10323749701.0, "pb": 2.33, "cloud_score": 8, "cloud_signals": ["MOMENTUM_OK", "TURNOVER_OK", "VOL_BOOM", "CAP_SWEET", "AMPLITUDE_ACTIVE"]}, {"code": "000008", "full_code": "sz000008", "name": "神州高铁", "price": 2.35, "pct_chg": 4.44, "change": 0.1, "volume": 491415.0, "amount": 111727018.72, "amplitude": 9.33, "turnover": 1.81, "pe": -52.49, "volume_ratio": 1.71, "high": 2.38, "low": 2.17, "open": 2.25, "prev_close": 2.25, "total_mv": 6383487555.0, "float_mv": 6383297837.0, "pb": 2.96, "cloud_score": 6, "cloud_signals": ["MOMENTUM_OK", "VOL_EXPAND", "CAP_SWEET", "AMPLITUDE_ACTIVE"]}, {"code": "000017", "full_code": "sz000017", "name": "深中华A", "price": 5.56, "pct_chg": 10.1, "change": 0.51, "volume": 215093.0, "amount": 115464741.14, "amplitude": 13.66, "turnover": 4.88, "pe": 156.64, "volume_ratio": 2.41, "high": 5.56, "low": 4.87, "open": 5.09, "prev_close": 5.05, "total_mv": 3831868227.0, "float_mv": 2450970048.0, "pb": 9.82, "cloud_score": 6, "cloud_signals": ["TURNOVER_OK", "VOL_BOOM", "CAP_SWEET", "AMPLITUDE_ACTIVE"]}, {"code": "000061", "full_code": "sz000061", "name": "农 产 品", "price": 5.51, "pct_chg": 3.77, "change": 0.2, "volume": 314407.0, "amount": 171139838.15, "amplitude": 8.47, "turnover": 1.75, "pe": 20.25, "volume_ratio": 1.4, "high": 5.63, "low": 5.18, "open": 5.31, "prev_close": 5.31, "total_mv": 10937136201.0, "float_mv": 9886659054.0, "pb": 1.28, "cloud_score": 6, "cloud_signals": ["MOMENTUM_OK", "VOL_EXPAND", "CAP_SWEET", "AMPLITUDE_ACTIVE"]}, {"code": "000153", "full_code": "sz000153", "name": "丰原药业", "price": 5.2, "pct_chg": 3.59, "change": 0.18, "volume": 114507.0, "amount": 58555818.2, "amplitude": 5.98, "turnover": 2.5, "pe": 16.32, "volume_ratio": 1.62, "high": 5.25, "low": 4.95, "open": 5.01, "prev_close": 5.02, "total_mv": 2416364714.0, "float_mv": 2386116184.0, "pb": 1.13, "cloud_score": 6, "cloud_signals": ["MOMENTUM_OK", "VOL_EXPAND", "CAP_SWEET", "AMPLITUDE_ACTIVE"]}, {"code": "000070", "full_code": "sz000070", "name": "特发信息", "price": 20.37, "pct_chg": -8.61, "change": -1.92, "volume": 1071879.0, "amount": 2235147384.95, "amplitude": 10.27, "turnover": 12.51, "pe": -463.8, "volume_ratio": 0.94, "high": 22.35, "low": 20.06, "open": 21.89, "prev_close": 22.29, "total_mv": 17689164371.0, "float_mv": 17451529825.0, "pb": 17.68, "cloud_score": 5, "cloud_signals": ["TURNOVER_HIGH", "CAP_SWEET", "AMPLITUDE_ACTIVE"]}, {"code": "000403", "full_code": "sz000403", "name": "派林生物", "price": 9.17, "pct_chg": 3.5, "change": 0.31, "volume": 207120.0, "amount": 187806369.0, "amplitude": 10.38, "turnover": 2.2, "pe": 94.86, "volume_ratio": 0.98, "high": 9.46, "low": 8.54, "open": 8.83, "prev_close": 8.86, "total_mv": 8715144030.0, "float_mv": 8626071170.0, "pb": 1.07, "cloud_score": 5, "cloud_signals": ["MOMENTUM_OK", "CAP_SWEET", "AMPLITUDE_ACTIVE"]}, {"code": "000411", "full_code": "sz000411", "name": "英特集团", "price": 9.23, "pct_chg": 2.56, "change": 0.23, "volume": 72464.0, "amount": 65063393.05, "amplitude": 7.89, "turnover": 1.29, "pe": 16.26, "volume_ratio": 1.31, "high": 9.33, "low": 8.62, "open": 8.95, "prev_close": 9.0, "total_mv": 5213557618.0, "float_mv": 5203282689.0, "pb": 0.96, "cloud_score": 5, "cloud_signals": ["MOMENTUM_WEAK", "VOL_EXPAND", "CAP_SWEET", "AMPLITUDE_ACTIVE"]}, {"code": "000012", "full_code": "sz000012", "name": "南  玻Ａ", "price": 4.69, "pct_chg": -2.29, "change": -0.11, "volume": 1154890.0, "amount": 545443374.73, "amplitude": 7.71, "turnover": 5.89, "pe": -36.16, "volume_ratio": 0.92, "high": 4.94, "low": 4.57, "open": 4.73, "prev_close": 4.8, "total_mv": 14269178724.0, "float_mv": 9189194845.0, "pb": 1.09, "cloud_score": 4, "cloud_signals": ["TURNOVER_OK", "CAP_SWEET", "AMPLITUDE_ACTIVE"]}, {"code": "000021", "full_code": "sz000021", "name": "深科技", "price": 58.86, "pct_chg": 10.0, "change": 5.35, "volume": 2396366.0, "amount": 13770298101.61, "amplitude": 6.19, "turnover": 15.22, "pe": 95.66, "volume_ratio": 1.18, "high": 58.86, "low": 55.55, "open": 56.0, "prev_close": 53.51, "total_mv": 92667405251.0, "float_mv": 92653826249.0, "pb": 7.12, "cloud_score": 4, "cloud_signals": ["TURNOVER_HIGH", "CAP_OK", "AMPLITUDE_ACTIVE"]}, {"code": "000037", "full_code": "sz000037", "name": "深南电A", "price": 8.87, "pct_chg": 0.0, "change": 0.0, "volume": 209835.0, "amount": 184292487.0, "amplitude": 5.52, "turnover": 6.19, "pe": 111.15, "volume_ratio": 0.79, "high": 8.99, "low": 8.5, "open": 8.8, "prev_close": 8.87, "total_mv": 5346504227.0, "float_mv": 3006115291.0, "pb": 3.2, "cloud_score": 4, "cloud_signals": ["TURNOVER_OK", "CAP_SWEET", "AMPLITUDE_ACTIVE"]}, {"code": "000048", "full_code": "sz000048", "name": "京基智农", "price": 21.21, "pct_chg": -2.39, "change": -0.52, "volume": 252256.0, "amount": 535958903.18, "amplitude": 8.24, "turnover": 4.77, "pe": -12.17, "volume_ratio": 0.7, "high": 22.3, "low": 20.51, "open": 21.81, "prev_close": 21.73, "total_mv": 11245600328.0, "float_mv": 11226511328.0, "pb": 2.99, "cloud_score": 4, "cloud_signals": ["TURNOVER_OK", "CAP_SWEET", "AMPLITUDE_ACTIVE"]}, {"code": "000060", "full_code": "sz000060", "name": "中金岭南", "price": 7.82, "pct_chg": 1.82, "change": 0.14, "volume": 2636690.0, "amount": 2076739519.82, "amplitude": 5.34, "turnover": 5.94, "pe": 17.24, "volume_ratio": 0.71, "high": 8.07, "low": 7.66, "open": 7.71, "prev_close": 7.68, "total_mv": 34729968622.0, "float_mv": 34729528747.0, "pb": 1.74, "cloud_score": 4, "cloud_signals": ["MOMENTUM_WEAK", "TURNOVER_OK", "CAP_OK", "AMPLITUDE_ACTIVE"]}, {"code": "000066", "full_code": "sz000066", "name": "中国长城", "price": 18.99, "pct_chg": 2.26, "change": 0.42, "volume": 2619826.0, "amount": 4899631045.68, "amplitude": 7.27, "turnover": 8.12, "pe": -183.15, "volume_ratio": 0.84, "high": 19.35, "low": 18.0, "open": 18.57, "prev_close": 18.57, "total_mv": 61257924681.0, "float_mv": 61253191424.0, "pb": 5.6, "cloud_score": 4, "cloud_signals": ["MOMENTUM_WEAK", "TURNOVER_OK", "CAP_OK", "AMPLITUDE_ACTIVE"]}, {"code": "000069", "full_code": "sz000069", "name": "华侨城Ａ", "price": 1.66, "pct_chg": 1.84, "change": 0.03, "volume": 596661.0, "amount": 96872099.18, "amplitude": 6.13, "turnover": 0.86, "pe": -2.44, "volume_ratio": 1.11, "high": 1.67, "low": 1.57, "open": 1.63, "prev_close": 1.63, "total_mv": 13342678368.0, "float_mv": 11451678956.0, "pb": 0.39, "cloud_score": 4, "cloud_signals": ["MOMENTUM_WEAK", "CAP_SWEET", "AMPLITUDE_ACTIVE"]}, {"code": "000151", "full_code": "sz000151", "name": "中成股份", "price": 10.8, "pct_chg": -1.73, "change": -0.19, "volume": 111603.0, "amount": 120024396.37, "amplitude": 5.73, "turnover": 3.62, "pe": 56.48, "volume_ratio": 0.65, "high": 11.11, "low": 10.48, "open": 11.04, "prev_close": 10.99, "total_mv": 3789787889.0, "float_mv": 3325694706.0, "pb": 4.33, "cloud_score": 4, "cloud_signals": ["TURNOVER_OK", "CAP_SWEET", "AMPLITUDE_ACTIVE"]}, {"code": "000422", "full_code": "sz000422", "name": "湖北宜化", "price": 13.58, "pct_chg": 2.41, "change": 0.32, "volume": 379943.0, "amount": 520265396.89, "amplitude": 3.62, "turnover": 3.59, "pe": 20.38, "volume_ratio": 0.73, "high": 13.99, "low": 13.51, "open": 13.53, "prev_close": 13.26, "total_mv": 14769400389.0, "float_mv": 14365694149.0, "pb": 2.48, "cloud_score": 4, "cloud_signals": ["MOMENTUM_WEAK", "TURNOVER_OK", "CAP_SWEET"]}]}