{"timestamp": "2026-07-17T05:27:36.125429", "min_score": 4, "count": 12, "stocks": [{"code": "000096", "full_code": "sz000096", "name": "广聚能源", "price": 7.86, "pct_chg": 1.68, "change": 0.13, "volume": 166288.0, "amount": 131777327.79, "amplitude": 5.69, "turnover": 3.26, "pe": 84.85, "volume_ratio": 3.5, "high": 8.1, "low": 7.66, "open": 7.73, "prev_close": 7.73, "total_mv": 4150080000.0, "float_mv": 4015265280.0, "pb": 1.51, "cloud_score": 7, "cloud_signals": ["MOMENTUM_WEAK", "TURNOVER_OK", "VOL_BOOM", "CAP_SWEET", "AMPLITUDE_ACTIVE"]}, {"code": "000014", "full_code": "sz000014", "name": "沙河股份", "price": 9.59, "pct_chg": -4.1, "change": -0.41, "volume": 153971.0, "amount": 151223635.4, "amplitude": 5.7, "turnover": 6.36, "pe": -68.36, "volume_ratio": 3.32, "high": 10.12, "low": 9.55, "open": 9.9, "prev_close": 10.0, "total_mv": 2321223288.0, "float_mv": 2321223288.0, "pb": 1.68, "cloud_score": 6, "cloud_signals": ["TURNOVER_OK", "VOL_BOOM", "CAP_SWEET", "AMPLITUDE_ACTIVE"]}, {"code": "000037", "full_code": "sz000037", "name": "深南电A", "price": 9.2, "pct_chg": 10.05, "change": 0.84, "volume": 294241.0, "amount": 265101479.5, "amplitude": 11.12, "turnover": 8.68, "pe": 115.28, "volume_ratio": 4.01, "high": 9.2, "low": 8.27, "open": 8.33, "prev_close": 8.36, "total_mv": 5545415883.0, "float_mv": 3117954980.0, "pb": 3.32, "cloud_score": 6, "cloud_signals": ["TURNOVER_OK", "VOL_BOOM", "CAP_SWEET", "AMPLITUDE_ACTIVE"]}, {"code": "000400", "full_code": "sz000400", "name": "许继电气", "price": 20.81, "pct_chg": 4.31, "change": 0.86, "volume": 272111.0, "amount": 562566482.28, "amplitude": 6.67, "turnover": 2.69, "pe": 47.72, "volume_ratio": 3.46, "high": 21.18, "low": 19.85, "open": 19.9, "prev_close": 19.95, "total_mv": 21197529002.0, "float_mv": 21053503200.0, "pb": 1.76, "cloud_score": 6, "cloud_signals": ["MOMENTUM_OK", "VOL_BOOM", "CAP_OK", "AMPLITUDE_ACTIVE"]}, {"code": "000007", "full_code": "sz000007", "name": "全新好", "price": 9.45, "pct_chg": -6.44, "change": -0.65, "volume": 61859.0, "amount": 60852468.0, "amplitude": 8.51, "turnover": 1.79, "pe": -377.06, "volume_ratio": 1.25, "high": 10.19, "low": 9.33, "open": 10.09, "prev_close": 10.1, "total_mv": 3273934016.0, "float_mv": 3273934016.0, "pb": 18.28, "cloud_score": 4, "cloud_signals": ["VOL_EXPAND", "CAP_SWEET", "AMPLITUDE_ACTIVE"]}, {"code": "000031", "full_code": "sz000031", "name": "大悦城", "price": 2.09, "pct_chg": -5.0, "change": -0.11, "volume": 336665.0, "amount": 72494726.0, "amplitude": 6.36, "turnover": 0.79, "pe": -10.13, "volume_ratio": 1.33, "high": 2.23, "low": 2.09, "open": 2.19, "prev_close": 2.2, "total_mv": 8958394879.0, "float_mv": 8958376825.0, "pb": 0.88, "cloud_score": 4, "cloud_signals": ["VOL_EXPAND", "CAP_SWEET", "AMPLITUDE_ACTIVE"]}, {"code": "000065", "full_code": "sz000065", "name": "北方国际", "price": 9.0, "pct_chg": 1.01, "change": 0.09, "volume": 126882.0, "amount": 114302776.93, "amplitude": 3.25, "turnover": 1.3, "pe": 23.66, "volume_ratio": 1.53, "high": 9.16, "low": 8.87, "open": 8.91, "prev_close": 8.91, "total_mv": 10452979431.0, "float_mv": 8774660592.0, "pb": 0.95, "cloud_score": 4, "cloud_signals": ["MOMENTUM_WEAK", "VOL_EXPAND", "CAP_SWEET"]}, {"code": "000070", "full_code": "sz000070", "name": "特发信息", "price": 13.5, "pct_chg": -8.66, "change": -1.28, "volume": 425749.0, "amount": 594424148.27, "amplitude": 9.2, "turnover": 4.97, "pe": -307.38, "volume_ratio": 0.91, "high": 14.76, "low": 13.4, "open": 14.65, "prev_close": 14.78, "total_mv": 11723304812.0, "float_mv": 11565815054.0, "pb": 11.72, "cloud_score": 4, "cloud_signals": ["TURNOVER_OK", "CAP_SWEET", "AMPLITUDE_ACTIVE"]}, {"code": "000088", "full_code": "sz000088", "name": "盐 田 港", "price": 4.37, "pct_chg": 0.69, "change": 0.03, "volume": 268297.0, "amount": 117888577.74, "amplitude": 1.84, "turnover": 0.85, "pe": 16.68, "volume_ratio": 2.07, "high": 4.42, "low": 4.34, "open": 4.35, "prev_close": 4.34, "total_mv": 22721742222.0, "float_mv": 13821810553.0, "pb": 1.27, "cloud_score": 4, "cloud_signals": ["VOL_BOOM", "CAP_SWEET"]}, {"code": "000089", "full_code": "sz000089", "name": "深圳机场", "price": 6.69, "pct_chg": 0.9, "change": 0.06, "volume": 230071.0, "amount": 155299577.46, "amplitude": 3.32, "turnover": 1.12, "pe": 13.29, "volume_ratio": 2.39, "high": 6.82, "low": 6.6, "open": 6.61, "prev_close": 6.63, "total_mv": 13719648015.0, "float_mv": 13719648015.0, "pb": 1.19, "cloud_score": 4, "cloud_signals": ["VOL_BOOM", "CAP_SWEET"]}, {"code": "000402", "full_code": "sz000402", "name": "金 融 街", "price": 2.4, "pct_chg": -3.23, "change": -0.08, "volume": 462666.0, "amount": 113580289.2, "amplitude": 5.65, "turnover": 1.55, "pe": 5.2, "volume_ratio": 1.6, "high": 2.54, "low": 2.4, "open": 2.46, "prev_close": 2.48, "total_mv": 7173431777.0, "float_mv": 7172769473.0, "pb": 0.36, "cloud_score": 4, "cloud_signals": ["VOL_EXPAND", "CAP_SWEET", "AMPLITUDE_ACTIVE"]}, {"code": "000417", "full_code": "sz000417", "name": "合百集团", "price": 5.8, "pct_chg": -7.2, "change": -0.45, "volume": 361728.0, "amount": 217997779.08, "amplitude": 7.52, "turnover": 4.64, "pe": 17.59, "volume_ratio": 0.91, "high": 6.24, "low": 5.77, "open": 6.17, "prev_close": 6.25, "total_mv": 4523328360.0, "float_mv": 4518359216.0, "pb": 0.96, "cloud_score": 4, "cloud_signals": ["TURNOVER_OK", "CAP_SWEET", "AMPLITUDE_ACTIVE"]}]}